yta_ai_llava/__init__.py
yta_ai_llava-0.0.1.dist-info/LICENSE
yta_ai_llava-0.0.1.dist-info/METADATA
yta_ai_llava-0.0.1.dist-info/WHEEL
yta_ai_llava-0.0.1.dist-info/RECORD
