Metadata-Version: 2.3
Name: yta-ai-llava
Version: 0.0.1
Summary: Youtube Autonomous AI Llava Module.
Author: danialcala94
Author-email: danielalcalavalera@gmail.com
Requires-Python: ==3.9
Classifier: Programming Language :: Python :: 3
Classifier: Programming Language :: Python :: 3.9
Requires-Dist: ollama (>=0.3.1,<1.0.0)
